[{"name":"Mouse Pad SteelSeries QcK Heavy Medium 63827/63836 (270 x 320 x 6mm)","tech":"\n                    <table>\n<tbody>\n<tr>\n<td>\n<p>Dòng sản phẩm</p>\n</td>\n<td>\n<p>Bàn di chuột</p>\n</td>\n</tr>\n<tr>\n<td>\n<p>Hãng sản xuất</p>\n</td>\n<td>\n<p>SteelSeries</p>\n</td>\n</tr>\n<tr>\n<td>\n<p>Mã sản phẩm</p>\n</td>\n<td>\n<p>SteelSeries QcK Heavy Medium 63827</p>\n</td>\n</tr>\n<tr>\n<td>\n<p>Kích thước</p>\n</td>\n<td>\n<p>270 x 320 x 6mm</p>\n</td>\n</tr>\n</tbody>\n</table>\n                ","avatar":"public/images/images-b9942f58-430d-426d-bda8-27fbfc98b5b0.jpg","price":"409.000","oldPrice":"","content":"<div class=\"title-n\">Đánh giá Mouse Pad SteelSeries QcK Heavy Medium 63827/63836 (270 x 320 x 6mm)</div>\n                <div class=\"list-n disaffter\">\n                    <div class=\"nd content-read\">\n                        <p style=\"text-align: center;\"><span style=\"font-size: 12pt;\"><strong><img src=\"/media/lib/20-04-2022/lcst-1.jpg\" alt=\"\"></strong></span></p>\n<p style=\"text-align: center;\"><span style=\"font-size: 12pt;\"><strong><a href=\"https://npcshop.vn/mouse-pad-steelseries-qck-heavy-medium-63827-63836\">Mouse Pad SteelSeries QcK Heavy</a>&nbsp;Medium 63827/63836</strong></span></p>\n<p style=\"text-align: center;\"><span style=\"font-size: 10pt;\">Mouse Pad SteelSeries QcK Heavy&nbsp;Medium 63827/63836 với kích thước&nbsp; 270 x 320 x 6mm , thiết kế mỏng, được làm từ cao su mềm chống trượt và có độ bám tốt. In hình SteelSeries giúp tăng thầm mỹ cho góc PC của bạn</span></p>\n<p style=\"text-align: center;\">&nbsp;<img src=\"/media/lib/20-04-2022/lcst-2.jpg\" alt=\"\"></p>\n                    </div>\n                    <div class=\"box-content-des-vm\">\n                        <a href=\"javascript:void(0)\" onclick=\"showProDetailDes()\">Xem thêm</a>\n                    </div>\n                </div>"},{"name":"Bàn di chuột chơi game Asus TUF GAMING P1","tech":"\n                    <table class=\"table table-striped\">\n<tbody>\n<tr>\n<td>\n<p>Thương hiệu</p>\n</td>\n<td>\n<p>ASUS</p>\n</td>\n</tr>\n<tr>\n<td>\n<p>Model</p>\n</td>\n<td>\n<p>TUF GAMING P1</p>\n</td>\n</tr>\n<tr>\n<td>\n<p>Kiểu</p>\n</td>\n<td>\n<p>Mềm mại</p>\n</td>\n</tr>\n<tr>\n<td>\n<p>Chất liệu</p>\n</td>\n<td>\n<p>Vải, đế cao su</p>\n</td>\n</tr>\n<tr>\n<td>\n<p>Vật liệu dưới cùng&nbsp;</p>\n</td>\n<td>\n<p>Cao su</p>\n</td>\n</tr>\n<tr>\n<td>\n<p>Kích thước</p>\n</td>\n<td>\n<p>260 x 360 x 2 mm</p>\n</td>\n</tr>\n<tr>\n<td>\n<p>Trọng lượng</p>\n</td>\n<td>\n<p>132 g</p>\n</td>\n</tr>\n<tr>\n<td>\n<p>Phụ kiện</p>\n</td>\n<td>\n<p>1 x Bàn di chuột TUF Gaming P1</p>\n</td>\n</tr>\n</tbody>\n</table>\n                ","avatar":"public/images/images-72006d1f-4b1e-488c-84d5-a364ef58f5e2.jpg","price":"300.000","oldPrice":"380.000","content":"<div class=\"title-n\">Đánh giá Bàn di chuột chơi game Asus TUF GAMING P1</div>\n                <div class=\"list-n disaffter\">\n                    <div class=\"nd content-read\">\n                        <p style=\"text-align: center;\"><strong>Bàn di chuột chơi game&nbsp;<a href=\"https://npcshop.vn/ban-di-chuot-choi-game-asus-tuf-gaming-p1\">Asus TUF GAMING P1</a></strong></p>\n<p style=\"text-align: center;\"><strong>TUF Gaming P1</strong> là tấm lót chuột di động có kích thước 360 x 260 mm với bề mặt vải mịn, tối ưu hóa cho việc chơi game để theo dõi chính xác và nhanh nhạy.&nbsp;Tấm lót chuột cao cấp này có bề mặt chống nước và đường khâu chống sờn để có độ bền hàng ngày, cùng với đế cao su chống trượt để đảm bảo nó luôn cố định ở vị trí - ngay cả trong những trận chiến căng thẳng&nbsp;nhất.</p>\n                    </div>\n                    <div class=\"box-content-des-vm\">\n                        <a href=\"javascript:void(0)\" onclick=\"showProDetailDes()\">Xem thêm</a>\n                    </div>\n                </div>"},{"name":"Tai nghe HyperX Cloud II Pink Gaming Headset","tech":"\n                    <table>\n<tbody>\n<tr>\n<td>Thương hiệu</td>\n<td>HyperX</td>\n</tr>\n<tr>\n<td>Model</td>\n<td>Cloud II Pink</td>\n</tr>\n<tr>\n<td>Kết nối</td>\n<td>Card âm thanh 3.5mm / USB</td>\n</tr>\n<tr>\n<td>Âm thanh</td>\n<td>Âm thanh vòm ảo 7.1</td>\n</tr>\n<tr>\n<td>Kích thước vòng tai nghe</td>\n<td>53mm</td>\n</tr>\n<tr>\n<td>Mic khử tiếng ồn</td>\n<td>Có thể tháo rời</td>\n</tr>\n<tr>\n<td>Vật liệu</td>\n<td>Memory foam + leatherette</td>\n</tr>\n<tr>\n<td>Trọng lượng</td>\n<td>275g</td>\n</tr>\n</tbody>\n</table>\n                ","avatar":"public/images/images-0065f525-a7b5-411e-9545-83538e6cad07.jpg","price":"2.490.000","oldPrice":"","content":"<div class=\"title-n\">Đánh giá Tai nghe HyperX Cloud II Pink Gaming Headset</div>\n                <div class=\"list-n disaffter\">\n                    <div class=\"nd content-read\">\n                        <p><img src=\"/media/lib/19-04-2022/screenshot_1650339608.png\" alt=\"\"></p>\n<p style=\"text-align: center;\"><span style=\"font-size: 12pt;\"><strong>Tai nghe Gaming <a href=\"https://npcshop.vn/tai-nghe-hyperx-cloud-ii-pink-gaming-headset\">HyperX Cloud II</a>&nbsp;- Gaming Headset, 7.1 Virtual Surround Sound, Memory Foam Ear Pads</strong></span></p>\n<p style=\"text-align: center;\"><strong>Tai nghe chơi game HyperX Cloud II Pink</strong> Gaming Headset có thiết kế nữ tính, màu sắc trẻ trung cùng nhiều công nghệ đi kèm giúp cho các nữ game thủ có trãi nghiệm chơi game tốt nhất..</p>\n<p><img src=\"/media/lib/19-04-2022/screenshot_1650339913.png\" alt=\"\"></p>\n                    </div>\n                    <div class=\"box-content-des-vm\">\n                        <a href=\"javascript:void(0)\" onclick=\"showProDetailDes()\">Xem thêm</a>\n                    </div>\n                </div>"},{"name":"Chuột Asus TUF Gaming M4 Wireless (12.000 dpi/2.4 Ghz/Bluetooth LE/100% PTFE)","tech":"\n                    <table style=\"border-collapse: collapse; width: 367pt; box-sizing: border-box; border-spacing: 0px; max-width: 100%; font-variant-ligatures: normal; font-variant-caps: normal; orphans: 2; widows: 2; -webkit-text-stroke-width: 0px; text-decoration-thickness: initial; text-decoration-style: initial; text-decoration-color: initial;\" width=\"489\">\n<tbody>\n<tr style=\"height: 15.75pt; box-sizing: border-box; margin-right: 0px; padding-bottom: 0px; padding-top: 0px;\">\n<td style=\"height: 15.75pt; width: 143pt; box-sizing: border-box;\" width=\"191\"><span style=\"box-sizing: border-box; margin-right: 0px; padding-bottom: 0px; padding-top: 0px;\"><span style=\"box-sizing: border-box; min-height: 0.01%; margin-right: 0px; padding-bottom: 0px; padding-top: 0px;\"><span style=\"box-sizing: border-box; overflow-x: auto; margin-right: 0px; padding-bottom: 0px; padding-top: 0px;\"><span style=\"box-sizing: border-box; line-height: 1.6; margin-right: 0px; padding-bottom: 0px; padding-top: 0px;\">Thương hiệu</span></span></span></span></td>\n<td style=\"border-left: none; width: 224pt; box-sizing: border-box;\" width=\"298\"><span style=\"box-sizing: border-box; margin-right: 0px; padding-bottom: 0px; padding-top: 0px;\"><span style=\"box-sizing: border-box; min-height: 0.01%; margin-right: 0px; padding-bottom: 0px; padding-top: 0px;\"><span style=\"box-sizing: border-box; overflow-x: auto; margin-right: 0px; padding-bottom: 0px; padding-top: 0px;\"><span style=\"box-sizing: border-box; line-height: 1.6; margin-right: 0px; padding-bottom: 0px; padding-top: 0px;\">Asus</span></span></span></span></td>\n</tr>\n<tr style=\"height: 15.75pt; box-sizing: border-box; margin-right: 0px; padding-bottom: 0px; padding-top: 0px;\">\n<td style=\"height: 15.75pt; width: 143pt; box-sizing: border-box;\" width=\"191\"><span style=\"box-sizing: border-box; margin-right: 0px; padding-bottom: 0px; padding-top: 0px;\"><span style=\"box-sizing: border-box; min-height: 0.01%; margin-right: 0px; padding-bottom: 0px; padding-top: 0px;\"><span style=\"box-sizing: border-box; overflow-x: auto; margin-right: 0px; padding-bottom: 0px; padding-top: 0px;\"><span style=\"box-sizing: border-box; line-height: 1.6; margin-right: 0px; padding-bottom: 0px; padding-top: 0px;\">Model</span></span></span></span></td>\n<td style=\"border-left: none; width: 224pt; box-sizing: border-box;\" width=\"298\"><span style=\"box-sizing: border-box; margin-right: 0px; padding-bottom: 0px; padding-top: 0px;\"><span style=\"box-sizing: border-box; min-height: 0.01%; margin-right: 0px; padding-bottom: 0px; padding-top: 0px;\"><span style=\"box-sizing: border-box; overflow-x: auto; margin-right: 0px; padding-bottom: 0px; padding-top: 0px;\"><span style=\"box-sizing: border-box; line-height: 1.6; margin-right: 0px; padding-bottom: 0px; padding-top: 0px;\">TUF Gaming M4 Wireless</span></span></span></span></td>\n</tr>\n<tr style=\"height: 15.0pt; box-sizing: border-box; margin-right: 0px; padding-bottom: 0px; padding-top: 0px;\">\n<td style=\"border-bottom: 1.0pt solid #DDDDDD; height: 30.75pt; border-top: none; width: 143pt; box-sizing: border-box;\" width=\"191\"><span style=\"box-sizing: border-box; margin-right: 0px; padding-bottom: 0px; padding-top: 0px;\"><span style=\"box-sizing: border-box; min-height: 0.01%; margin-right: 0px; padding-bottom: 0px; padding-top: 0px;\"><span style=\"box-sizing: border-box; overflow-x: auto; margin-right: 0px; padding-bottom: 0px; padding-top: 0px;\"><span style=\"box-sizing: border-box; line-height: 1.6; margin-right: 0px; padding-bottom: 0px; padding-top: 0px;\">Kết nối</span></span></span></span></td>\n<td style=\"border-top: none; border-left: none; width: 224pt; box-sizing: border-box;\" width=\"298\"><span style=\"box-sizing: border-box; margin-right: 0px; padding-bottom: 0px; padding-top: 0px;\"><span style=\"box-sizing: border-box; min-height: 0.01%; margin-right: 0px; padding-bottom: 0px; padding-top: 0px;\"><span style=\"box-sizing: border-box; overflow-x: auto; margin-right: 0px; padding-bottom: 0px; padding-top: 0px;\"><span style=\"box-sizing: border-box; line-height: 1.6; margin-right: 0px; padding-bottom: 0px; padding-top: 0px;\">Bluetooth 5.1,&nbsp;RF 2.4GHz</span></span></span></span></td>\n</tr>\n<tr style=\"height: 15.75pt; box-sizing: border-box; margin-right: 0px; padding-bottom: 0px; padding-top: 0px;\">\n<td style=\"height: 15.75pt; border-top: none; width: 143pt; box-sizing: border-box;\" width=\"191\"><span style=\"box-sizing: border-box; margin-right: 0px; padding-bottom: 0px; padding-top: 0px;\"><span style=\"box-sizing: border-box; min-height: 0.01%; margin-right: 0px; padding-bottom: 0px; padding-top: 0px;\"><span style=\"box-sizing: border-box; overflow-x: auto; margin-right: 0px; padding-bottom: 0px; padding-top: 0px;\"><span style=\"box-sizing: border-box; line-height: 1.6; margin-right: 0px; padding-bottom: 0px; padding-top: 0px;\">Kích thước</span></span></span></span></td>\n<td style=\"border-top: none; border-left: none; width: 224pt; box-sizing: border-box;\" width=\"298\"><span style=\"box-sizing: border-box; margin-right: 0px; padding-bottom: 0px; padding-top: 0px;\"><span style=\"box-sizing: border-box; min-height: 0.01%; margin-right: 0px; padding-bottom: 0px; padding-top: 0px;\"><span style=\"box-sizing: border-box; overflow-x: auto; margin-right: 0px; padding-bottom: 0px; padding-top: 0px;\"><span style=\"box-sizing: border-box; line-height: 1.6; margin-right: 0px; padding-bottom: 0px; padding-top: 0px;\">126 x 63.5 x39.6 mm</span></span></span></span></td>\n</tr>\n<tr style=\"height: 15.0pt; box-sizing: border-box; margin-right: 0px; padding-bottom: 0px; padding-top: 0px;\">\n<td style=\"border-bottom: 1.0pt solid #DDDDDD; height: 45.75pt; border-top: none; width: 143pt; box-sizing: border-box;\" width=\"191\"><span style=\"box-sizing: border-box; margin-right: 0px; padding-bottom: 0px; padding-top: 0px;\"><span style=\"box-sizing: border-box; min-height: 0.01%; margin-right: 0px; padding-bottom: 0px; padding-top: 0px;\"><span style=\"box-sizing: border-box; overflow-x: auto; margin-right: 0px; padding-bottom: 0px; padding-top: 0px;\"><span style=\"box-sizing: border-box; line-height: 1.6; margin-right: 0px; padding-bottom: 0px; padding-top: 0px;\">Khối lượng</span></span></span></span></td>\n<td style=\"border-top: none; border-left: none; width: 224pt; box-sizing: border-box;\" width=\"298\"><span style=\"box-sizing: border-box; margin-right: 0px; padding-bottom: 0px; padding-top: 0px;\"><span style=\"box-sizing: border-box; min-height: 0.01%; margin-right: 0px; padding-bottom: 0px; padding-top: 0px;\"><span style=\"box-sizing: border-box; overflow-x: auto; margin-right: 0px; padding-bottom: 0px; padding-top: 0px;\"><span style=\"box-sizing: border-box; line-height: 1.6; margin-right: 0px; padding-bottom: 0px; padding-top: 0px;\">62 g không tính pin &amp; dongle<br> 77 g với 1 viên pin AAA<br> 86 g với 1 viên pin AA<br> </span></span></span></span></td>\n</tr>\n<tr style=\"height: 15.75pt; box-sizing: border-box; margin-right: 0px; padding-bottom: 0px; padding-top: 0px;\">\n<td style=\"height: 15.75pt; border-top: none; width: 143pt; box-sizing: border-box;\" width=\"191\"><span style=\"box-sizing: border-box; margin-right: 0px; padding-bottom: 0px; padding-top: 0px;\"><span style=\"box-sizing: border-box; min-height: 0.01%; margin-right: 0px; padding-bottom: 0px; padding-top: 0px;\"><span style=\"box-sizing: border-box; overflow-x: auto; margin-right: 0px; padding-bottom: 0px; padding-top: 0px;\"><span style=\"box-sizing: border-box; line-height: 1.6; margin-right: 0px; padding-bottom: 0px; padding-top: 0px;\">DPI</span></span></span></span></td>\n<td style=\"border-top: none; border-left: none; width: 224pt;\" width=\"298\">12000 dpi</td>\n</tr>\n<tr style=\"height: 15.0pt; box-sizing: border-box; margin-right: 0px; padding-bottom: 0px; padding-top: 0px;\">\n<td style=\"border-bottom: 1.0pt solid #DDDDDD; height: 90.75pt; border-top: none; width: 143pt; box-sizing: border-box;\" width=\"191\"><span style=\"box-sizing: border-box; margin-right: 0px; padding-bottom: 0px; padding-top: 0px;\"><span style=\"box-sizing: border-box; min-height: 0.01%; margin-right: 0px; padding-bottom: 0px; padding-top: 0px;\"><span style=\"box-sizing: border-box; overflow-x: auto; margin-right: 0px; padding-bottom: 0px; padding-top: 0px;\"><span style=\"box-sizing: border-box; line-height: 1.6; margin-right: 0px; padding-bottom: 0px; padding-top: 0px;\">Thời lượng pin</span></span></span></span></td>\n<td style=\"border-top: none; border-left: none; width: 224pt; box-sizing: border-box;\" width=\"298\"><span style=\"box-sizing: border-box; margin-right: 0px; padding-bottom: 0px; padding-top: 0px;\"><span style=\"box-sizing: border-box; min-height: 0.01%; margin-right: 0px; padding-bottom: 0px; padding-top: 0px;\"><span style=\"box-sizing: border-box; overflow-x: auto; margin-right: 0px; padding-bottom: 0px; padding-top: 0px;\"><span style=\"box-sizing: border-box; line-height: 1.6; margin-right: 0px; padding-bottom: 0px; padding-top: 0px;\">Pin AA: <br> + RF 2.4GHz: 134 h<br> + Bluetooth 5.1: 232 h<br> Pin AAA:<br> + RF 2.4GHz: 53 h<br> + Bluetooth 5.1: 100 h</span></span></span></span></td>\n</tr>\n</tbody>\n</table>\n<p>&nbsp;</p>\n                ","avatar":"public/images/images-aa174dbf-9aad-4af9-903c-c3069286ae51.jpg","price":"1.190.000","oldPrice":"","content":"<div class=\"title-n\">Đánh giá Chuột Asus TUF Gaming M4 Wireless (12.000 dpi/2.4 Ghz/Bluetooth LE/100% PTFE)</div>\n                <div class=\"list-n disaffter\">\n                    <div class=\"nd content-read\">\n                        <p style=\"text-align: center;\"><span style=\"font-size: 12pt;\"><strong><img src=\"/media/lib/18-04-2022/screenshot_1650272051.png\" alt=\"\"></strong></span></p>\n<p style=\"text-align: center;\"><span style=\"font-size: 12pt;\"><strong><a href=\"https://npcshop.vn/chuot-asus-tuf-gaming-m4-wireless\">Chuột Asus TUF Gaming M4 Wireless</a></strong></span></p>\n<p style=\"text-align: center;\"><span style=\"font-size: 10pt;\"><strong>Chuột chơi game TUF Gaming M4 wireless</strong> được thiết kế để sử dụng trong một khoảng thời gian dài với độ chính xác cao, mang lại trãi nghiệm tốt nhất cho mọi game thủ.</span></p>\n<p style=\"text-align: center;\"><span style=\"font-size: 10pt;\"><img src=\"/media/lib/18-04-2022/2022-04-18_1555571.jpg\" alt=\"\"></span></p>\n<p style=\"text-align: center;\">&nbsp;</p>\n<p style=\"text-align: center;\">&nbsp;</p>\n<p style=\"text-align: center;\">&nbsp;</p>\n                    </div>\n                    <div class=\"box-content-des-vm\">\n                        <a href=\"javascript:void(0)\" onclick=\"showProDetailDes()\">Xem thêm</a>\n                    </div>\n                </div>"},{"name":"Bàn phím cơ Gaming DAREU EK1280 RGB Red Switch (Đen)","tech":"\n                    <table>\n<tbody>\n<tr>\n<td>\n<p>Hãng sản xuất</p>\n</td>\n<td>\n<p>DareU</p>\n</td>\n</tr>\n<tr>\n<td>\n<p>Model&nbsp;</p>\n</td>\n<td>\n<p>EK1280</p>\n</td>\n</tr>\n<tr>\n<td>\n<p>Loại bàn phím</p>\n</td>\n<td>\n<p>Bàn phím cơ</p>\n</td>\n</tr>\n<tr>\n<td>\n<p>Chuẩn giao tiếp</p>\n</td>\n<td>\n<p>USB 2.0</p>\n</td>\n</tr>\n<tr>\n<td>\n<p>Màu sắc</p>\n</td>\n<td>\n<p>Đen</p>\n</td>\n</tr>\n<tr>\n<td>\n<p>Màu led</p>\n</td>\n<td>\n<p>RGB</p>\n</td>\n</tr>\n<tr>\n<td>\n<p>Loại switch</p>\n</td>\n<td>\n<p>\"D\" switch&nbsp;Red DareU</p>\n</td>\n</tr>\n<tr>\n<td>\n<p>Phù hợp nhu cầu</p>\n</td>\n<td>\n<p>Chơi game, gõ văn bản</p>\n</td>\n</tr>\n</tbody>\n</table>\n                ","avatar":"public/images/images-b0ed577b-72f5-4cc3-a57b-f74aa69a3ccb.jpg","price":"980.000","oldPrice":"","content":"<div class=\"title-n\">Đánh giá Bàn phím cơ Gaming DAREU EK1280 RGB Red Switch (Đen)</div>\n                <div class=\"list-n disaffter\">\n                    <div class=\"nd content-read\">\n                        <p style=\"text-align: center;\" align=\"center\"><span style=\"font-size: 12pt;\"><strong><img src=\"/media/lib/18-04-2022/46536_ban-phim-co-dareu-ek1280-rgb-mechanical-blue-d-switch-black-5.jpg\" alt=\"\"></strong></span></p>\n<p align=\"center\"><span style=\"font-size: 12pt;\"><strong>Bàn phím cơ Gaming&nbsp;<a href=\"https://npcshop.vn/ban-phim-co-gaming-dareu-ek1280-rgb-red-switch\">DAREU EK1280 RGB Red Switch</a></strong></span></p>\n<p align=\"center\">&nbsp;<strong>Bàn phím Keyboard Dareu EK1280&nbsp;Red Switch RGB</strong> Mechanical Thiết kế Fullsize 104 phím, Sử dụng công nghệ D switch độc quyền trên bàn phím DareU, Được trang bị đèn led RGB</p>\n<p align=\"center\">&nbsp;</p>\n                    </div>\n                    <div class=\"box-content-des-vm\">\n                        <a href=\"javascript:void(0)\" onclick=\"showProDetailDes()\">Xem thêm</a>\n                    </div>\n                </div>"}]