[{"name":"NPC Remus - Bộ case In-Win D-Frame 2.0 cùng bộ tản nhiệt nước Bitspower","tech":"\n                    <table style=\"height: 194px;\" width=\"527\">\n<tbody>\n<tr>\n<td><span style=\"font-size: 10pt;\"><strong>CPU</strong></span></td>\n<td><span style=\"font-size: 10pt;\">AMD Ryzen 9 - 5950X</span></td>\n</tr>\n<tr>\n<td><span style=\"font-size: 10pt;\"><strong>MAIN</strong></span></td>\n<td><span style=\"font-size: 10pt;\">MSI MEG X570 GODLKE</span></td>\n</tr>\n<tr>\n<td><span style=\"font-size: 10pt;\"><strong>Ram</strong></span></td>\n<td><span style=\"font-size: 10pt;\">G.Skill Trident Z Neo 64GB (4x16GB) DDR4 3000MHz</span></td>\n</tr>\n<tr>\n<td><span style=\"font-size: 10pt;\"><strong>VGA</strong></span></td>\n<td><span style=\"font-size: 10pt;\">ASUS ROG Strix GeForce RTX 2080 Ti OC Edition 11GB GDDR6</span></td>\n</tr>\n<tr>\n<td><span style=\"font-size: 10pt;\"><strong>SSD</strong></span></td>\n<td><span style=\"font-size: 10pt;\">2 x Western Digital Black SN750 NVMe&nbsp; 500GB</span></td>\n</tr>\n<tr>\n<td><span style=\"font-size: 10pt;\"><strong>HDD</strong></span></td>\n<td><span style=\"font-size: 10pt;\">Có tùy chọn&nbsp;<a href=\"https://npcshop.vn/o-cung-hdd\">Nâng Cấp</a></span></td>\n</tr>\n<tr>\n<td><span style=\"font-size: 10pt;\"><strong>CASE</strong></span></td>\n<td><span style=\"font-size: 10pt;\">In-Win D-Frame 2.0</span></td>\n</tr>\n<tr>\n<td><span style=\"font-size: 10pt;\"><strong>PSU</strong></span></td>\n<td><span style=\"font-size: 10pt;\">In-Win SIII-1065 W</span></td>\n</tr>\n<tr>\n<td><span style=\"font-size: 10pt;\"><strong>FAN</strong></span></td>\n<td><span style=\"font-size: 10pt;\">Bitspower Notos Xtal 120 Fan Digital RGB</span></td>\n</tr>\n<tr>\n<td><span style=\"font-size: 10pt;\"><strong>Tản nhiệt nước</strong></span></td>\n<td><span style=\"font-size: 10pt;\">Bitspower Pump D5 Vario và các thành phần làm mát nước đầy đủ Bitspower.</span></td>\n</tr>\n<tr>\n<td><span style=\"font-size: 10pt;\"><strong>Coolant </strong></span></td>\n<td><span style=\"font-size: 10pt;\">Coolant Mayhems X1 Clear 1 Ltr Premixed V2.</span></td>\n</tr>\n<tr>\n<td><span style=\"font-size: 10pt;\"><strong>Custom</strong></span></td>\n<td><span style=\"font-size: 10pt;\">NPC Distro Plate Custom x2</span></td>\n</tr>\n</tbody>\n</table>\n<p><span style=\"font-size: 10pt;\">&nbsp;</span></p>\n                ","avatar":"public/images/images-a052b624-c695-4bbe-bfc0-9b5c894dcc70.jpg","price":"220.000.000","oldPrice":"","content":"<div class=\"title-n\">Đánh giá NPC Remus - Bộ case In-Win D-Frame 2.0 cùng bộ tản nhiệt nước Bitspower</div>\n                <div class=\"list-n disaffter\">\n                    <div class=\"nd content-read\">\n                        <div class=\"content-text overflow-hidden position-relative\">\n<p style=\"text-align: center;\"><span style=\"font-size: 14pt;\"><strong>NPC Remus - Bộ case In-Win D-Frame 2.0</strong></span></p>\n<p style=\"text-align: center;\"><img src=\"/media/lib/24-01-2022/3.jpg\" alt=\"\" width=\"75%\"></p>\n<p style=\"text-align: center;\"><span style=\"font-size: 8pt;\"><em>In-Win D-Frame 2.0 Custom nước tại Nguyễn PC</em></span></p>\n<p style=\"text-align: left;\"><span style=\"font-size: 12pt;\"><strong><a href=\"/case-inwin-d-frame-2-0\">In-Win D-Frame 2.0</a></strong> là chiếc case đình đám không kém Z Tower. <strong>In-Win D-Frame 2.0</strong> cũng chỉ sản xuất giới hạn 500 chiếc trên toàn thế giới, chiếc ở tại <strong>Nguyễn PC</strong> mang số 414/500. Với mức giá 29.900.000VNĐ thì <strong>In-Win D-Frame 2.0</strong> là một lựa chọn phù hợp cho những bạn đang build pc tản nhiệt nước chi phí từ 100-200 triệu. Có thể hình dung D-Frame như là 1 chiếc xe đua khi được thiết kế dựa trên sự tự do, cá tính và bốc đồng của những chiếc mô tô địa hình.<br></span></p>\n<p style=\"text-align: left;\">&nbsp;</p>\n<p style=\"text-align: center;\"><span style=\"font-size: 12pt;\"><img style=\"display: block; margin-left: auto; margin-right: auto;\" src=\"/media/lib/24-01-2022/13.jpg\" alt=\"\" width=\"75%\"><span style=\"font-size: 8pt;\"><em>In-Win D-Frame 2.0 Custom nước tại Nguyễn PC</em></span></span></p>\n<p style=\"text-align: left;\"><span style=\"font-size: 12pt;\">Linh kiện được <a href=\"/buildpc\">Build </a>kèm với <strong>In-Win D-Frame 2.0</strong>:<br></span></p>\n<p style=\"text-align: left;\"><span style=\"font-size: 12pt;\">&nbsp;- <strong>Mainboard</strong>: <a href=\"/mainboard-msi-meg-x570-godlike\">MSI MEG X570 GODLIKE</a></span></p>\n<p style=\"text-align: left;\"><span style=\"font-size: 12pt;\">&nbsp;- <strong>CPU</strong>: <a href=\"/cpu-amd-ryzen-9-5950x-4-9-ghz-72mb-16-cores-32-threads-105w-socket-am4\">AMD Ryzen 9 - 5950X</a></span></p>\n<p style=\"text-align: left;\"><span style=\"font-size: 12pt;\">&nbsp;- <strong>VGA</strong>: <a href=\"/vga-asus-rog-strix-geforce-rtx-2080-ti-oc-edition-11gb-gddr6\">ASUS ROG Strix GeForce RTX 2080 Ti OC Edition 11GB GDDR6</a></span></p>\n<p style=\"text-align: left;\"><span style=\"font-size: 12pt;\">&nbsp;- <strong>RAM</strong>: <a href=\"/ram-gskill-trident-z-rgb-royal-gold-64gb-4x16gb-ddr4-3000mhz\">G.Skill Trident Z Royal Gold Edition 64GB (4x16GB) DDR4 3000MHz</a></span></p>\n<p style=\"text-align: left;\"><span style=\"font-size: 12pt;\">&nbsp;- <strong>SSD</strong>: <a href=\"/ssd-wd-sn750-black-1tb-m-2-2280-pcie-nvme-3x4\">Western Digital SN750 Black 1TB M.2 2280 PCIe NVMe 3x4</a></span></p>\n<p style=\"text-align: left;\">&nbsp;</p>\n<p style=\"text-align: left;\">&nbsp;<img style=\"display: block; margin-left: auto; margin-right: auto;\" src=\"/media/lib/24-01-2022/11.jpg\" alt=\"\" width=\"75%\"></p>\n<p style=\"text-align: center;\"><span style=\"font-size: 12pt;\"><span style=\"font-size: 8pt;\"><em>In-Win D-Frame 2.0 Custom nước tại Nguyễn PC</em></span></span></p>\n<p style=\"text-align: left;\">&nbsp;</p>\n<p style=\"text-align: left;\"><span style=\"font-size: 12pt;\">Có lẽ <strong>In-Win D-Frame 2.0</strong> đẹp nhất độc nhất là khi thay thế toàn bộ chassis định hình bằng tấm nước custom với kích thước hoàn toàn giống so với bản gốc.</span></p>\n<p style=\"text-align: center;\"><span style=\"font-size: 12pt;\"><img style=\"display: block; margin-left: auto; margin-right: auto;\" src=\"/media/lib/24-01-2022/5.jpg\" alt=\"\" width=\"75%\"><span style=\"font-size: 8pt;\"><em>In-Win D-Frame 2.0 Custom nước tại Nguyễn PC</em></span></span></p>\n<p style=\"text-align: left;\">&nbsp;</p>\n<p style=\"text-align: left;\"><span style=\"font-size: 12pt;\">Với sự sáng tạo của những <strong>Modder Nguyễn PC</strong> thì những điều không thể cũng trở nên dễ dàng hơn, việc thiết kế tấm nước cho D-Frame đã biến D-Frame thành một tác phẩm nghệ thuật của <strong>PC Custom Nước</strong>. Ngoài tấm nước ở mặt lưng thì <strong>Nguyễn PC</strong> còn thiết kế tấm nước theo yêu cầu là tấm nước có khắc Tên Chủ Nhân (Bật mí 1 chút về chủ nhân của em nó là 1 cô gái rất dễ thương và cô ấy tên là Helen).</span></p>\n<p style=\"text-align: center;\"><span style=\"font-size: 12pt;\"><img style=\"display: block; margin-left: auto; margin-right: auto;\" src=\"/media/lib/24-01-2022/12.jpg\" alt=\"\" width=\"75%\"><span style=\"font-size: 8pt;\"><em>In-Win D-Frame 2.0 Custom nước tại Nguyễn PC</em></span></span></p>\n<p style=\"text-align: center;\">&nbsp;</p>\n<p style=\"text-align: left;\"><span style=\"font-size: 12pt;\">Với những chiếc Case tải nhiệt nước nhiều linh kiện thì việc đi dây gọn gàng là 1 phần rất khó, đòi hỏi Modder phải có tính tỉ mỉ cao. Để làm gọn dây nhất có thể,<strong> Nguyễn PC</strong> đã thiết kế dây đi trong tấm nước tản nhiệt như hình. Anh em cũng có thể thấy những đường dây đi trong tấm nước giúp việc đi dây rất dễ dàng và thẩm mỹ hơn.</span></p>\n<p style=\"text-align: center;\"><span style=\"font-size: 12pt;\"> <img style=\"display: block; margin-left: auto; margin-right: auto;\" src=\"/media/lib/24-01-2022/6.jpg\" alt=\"\" width=\"75%\"><span style=\"font-size: 8pt;\"><em>In-Win D-Frame 2.0 Custom nước tại Nguyễn PC</em></span></span></p>\n<p style=\"text-align: left;\">&nbsp;</p>\n<p style=\"text-align: left;\"><span style=\"font-size: 12pt;\">Ngoài tấm nước tự thiết kế thì linh kiện tản nhiệt Custom Nước như Block tản nhiệt VGA, CPU Pump... còn lại của bộ<strong> In-Win D-Frame 2.0</strong> Nguyễn PC sử dụng toàn bộ là của hãng <strong>Bitspower</strong> anh em nhé.</span></p>\n<p style=\"text-align: left;\">&nbsp;</p>\n<p style=\"text-align: left;\"><span style=\"font-size: 12pt;\">Anh em có thể xem thêm video của <strong>In-Win D-Frame 2.0</strong> bên dưới nhé và đừng quên ủng hộ 1 Like 1 Subscribe cho <strong>Nguyễn PC</strong> nhé.</span></p>\n<p style=\"text-align: left;\"><span style=\"font-size: 12pt;\"><img style=\"display: block; margin-left: auto; margin-right: auto;\" src=\"/media/lib/24-01-2022/4.jpg\" alt=\"\" width=\"75%\"></span></p>\n<p style=\"text-align: left;\">&nbsp;</p>\n<p style=\"text-align: left;\"><span style=\"font-size: 12pt;\">Chi phí cuối cùng của <strong>In-Win D-Frame 2.0 NPC Remus</strong> là: 220.000.000 VNĐ</span></p>\n<p style=\"text-align: left;\"><span style=\"font-size: 12pt;\">Với những thiết kế từ Nguyễn PC đã giúp In-Win D-Frame 2.0 lung linh hơn lộng lẫy hơn bao giờ hết và em ấy xứng đáng&nbsp; đứng ở TOP 2 trong những case Nguyễn PC đã từng build.</span></p>\n</div>\n                    </div>\n                    <div class=\"box-content-des-vm\">\n                        <a href=\"javascript:void(0)\" onclick=\"showProDetailDes()\">Xem thêm</a>\n                    </div>\n                </div>"},{"name":"NPC - In-Win Z-Tower 069","tech":"\n                    <table style=\"height: 194px;\" width=\"527\">\n<tbody>\n<tr>\n<td><span style=\"font-size: 10pt;\"><strong>CPU</strong></span></td>\n<td><span style=\"font-size: 10pt;\">Intel Core i9 - 11900K<br></span></td>\n</tr>\n<tr>\n<td><span style=\"font-size: 10pt;\"><strong>MAIN</strong></span></td>\n<td>ASUS ROG Maximus Z590 XIII Extreme Glacial</td>\n</tr>\n<tr>\n<td><span style=\"font-size: 10pt;\"><strong>VGA</strong></span></td>\n<td>2 x MSI GeForce RTX 3090 SUPRIM X 24GB</td>\n</tr>\n<tr>\n<td><span style=\"font-size: 10pt;\"><strong>SSD</strong></span></td>\n<td><span style=\"font-size: 10pt;\">2 x Samsung 980 PRO PCIe Gen 4.0 x4 NVMe V-NAND M.2 2280 2TB<br></span></td>\n</tr>\n<tr>\n<td><span style=\"font-size: 10pt;\"><strong>HDD</strong></span></td>\n<td><span style=\"font-size: 10pt;\">Có tùy chọn&nbsp;<a href=\"https://npcshop.vn/o-cung-hdd\">Nâng Cấp</a></span></td>\n</tr>\n<tr>\n<td><span style=\"font-size: 10pt;\"><strong>CASE</strong></span></td>\n<td><span style=\"font-size: 10pt;\">In-Win Z-Tower<br></span></td>\n</tr>\n<tr>\n<td><span style=\"font-size: 10pt;\"><strong>PSU</strong></span></td>\n<td><span style=\"font-size: 10pt;\">CORSAIR HX1200 - 1200 Watt 80 Plus Platinum<br></span></td>\n</tr>\n<tr>\n<td><span style=\"font-size: 10pt;\"><strong>FAN</strong></span></td>\n<td><span style=\"font-size: 10pt;\">Bitspower Notos Xtal 120 Fan Digital RGB</span></td>\n</tr>\n<tr>\n<td><span style=\"font-size: 10pt;\"><strong>Tản nhiệt nước</strong></span></td>\n<td><span style=\"font-size: 10pt;\">Bitspower Pump D5 Vario và các thành phần làm mát nước đầy đủ Bitspower.</span></td>\n</tr>\n<tr>\n<td><span style=\"font-size: 10pt;\"><strong>Coolant </strong></span></td>\n<td><span style=\"font-size: 10pt;\">Coolant Mayhems X1 Clear 1 Ltr Premixed V2.</span></td>\n</tr>\n<tr>\n<td><span style=\"font-size: 10pt;\"><strong>Custom</strong></span></td>\n<td><span style=\"font-size: 10pt;\">NPC Distro Plate Custom<br></span></td>\n</tr>\n</tbody>\n</table>\n<p><span style=\"font-size: 10pt;\">&nbsp;</span></p>\n                ","avatar":"public/images/images-5da86d96-399b-431e-bdaf-c1df63dc60e8.jpg","price":"400.000.000","oldPrice":"","content":"<div class=\"title-n\">Đánh giá NPC - In-Win Z-Tower 069</div>\n                <div class=\"list-n disaffter\">\n                    <div class=\"nd content-read\">\n                        <p style=\"text-align: center;\"><span style=\"font-size: 14pt;\"><strong>NPC - Inwin Z-Tower 069</strong></span></p>\n<p>&nbsp;<img style=\"display: block; margin-left: auto; margin-right: auto;\" src=\"/media/lib/25-01-2022/673d86a6372bfa75a33a.jpg\" alt=\"\" width=\"75%\"></p>\n<p>&nbsp;</p>\n<p><span style=\"font-size: 12pt;\"><strong><a href=\"/case-inwin-z-tower\">Inwin Z-Tower</a></strong>&nbsp;được biết đến là mẫu case cho máy tính có gái trị mắc nhất hiện tại vưới mức giá 145.000.000 VNĐ đang được bán tại Nguyễn PC. Đặc biệt hơn nữa là chiếc Inwin Z Tower này chỉ giới hạn 100 chiếc trên toàn thế giới.</span></p>\n<p style=\"text-align: center;\">&nbsp;<img style=\"display: block; margin-left: auto; margin-right: auto;\" src=\"/media/lib/25-01-2022/1601_263156597_448030803554724_6170771592692753678_n.jpg\" alt=\"\" width=\"75%\"><span style=\"font-size: 12pt;\"><span style=\"font-size: 8pt; color: #000000; font-family: 'times new roman', times;\">*Chiếc Inwin Z tower tại Nguyễn PC mang số 069/100.</span></span></p>\n<p>&nbsp;</p>\n<p><span style=\"font-size: 12pt;\">Nhìn tổng thể thì chiếc Inwin Z Tower giống như 1 gốc cây đại thụ vài trăm năm tuổi. và đúng là chiếc case này kiểu dáng này sau nhiều năm nữa thì cũng không thể lỗi thời mà ngày càng có giá trị về thẩm mỹ và giới hạn vì em nó chỉ có 100 chiếc trên toàn thế giới.</span></p>\n<p>&nbsp;</p>\n<p style=\"text-align: center;\"><img style=\"display: block; margin-left: auto; margin-right: auto;\" src=\"/media/lib/25-01-2022/1601_263433927_448030733554731_8738842467991707783_n.jpg\" alt=\"\" width=\"75%\"><span style=\"font-size: 12pt;\"><span style=\"font-size: 12pt; color: #000000; font-family: 'times new roman', times;\"><span style=\"font-size: 8pt;\">*Hình ảnh trông như cây đại cổ thụ của&nbsp;Inwin Z Tower.</span></span></span></p>\n<p><span style=\"font-size: 12pt;\">Để nằm trong chiếc Inwin Z Tower thì không thể thiếu những linh kiện giá cao nhất, chất nhất từ các hãng linh kiện PC hàng đầu.</span></p>\n<p>&nbsp;</p>\n<p><strong><span style=\"font-size: 12pt;\">Bảng linh kiện ẩn mình trong Inwin Z Tower:</span></strong></p>\n<p><span style=\"font-size: 12pt;\">&nbsp;- <strong>Mainboard</strong>: <strong><a href=\"/mainboard-asus-rog-z590-maximus-xiii-extreme-glacial-den\">ASUS ROG Z590 Maximus XIII Extreme Glacial</a></strong><br></span></p>\n<p><span style=\"font-size: 12pt;\">&nbsp;- <strong>CPU</strong>: <strong><a href=\"/cpu-intel-core-i9-11900k\">Intel Core i9 - 11900K</a></strong><br></span></p>\n<p><span style=\"font-size: 12pt;\">&nbsp;- <strong>VGA</strong>: 2x&nbsp;<strong><a href=\"/vga-msi-geforce-rtx-3090-suprim-x-24g-den\">MSI GeForce RTX 3090 SUPRIM X 24GB</a></strong></span></p>\n<p><span style=\"font-size: 12pt;\">&nbsp;- <strong>RAM</strong>: <strong><a href=\"/ram-g-skill-tridenz-rgb-royal-elite-gold-16gb-2x8gb-ddr4-3600mhz\">G.Skill Trident Z Royal Elite 64GB (4x16GB) DDR4 3600MHz</a></strong><br></span></p>\n<p><span style=\"font-size: 12pt;\">&nbsp;- <strong>SSD</strong>: 2x <strong><a href=\"/ssd-samsung-980-pro-2tb-m-2-nvme-pcie-gen4x4-mz-v8p2t0bw-den\">Samsung 980 Pro PCIe Gen 4.0 x4 NVMe V-NAND M.2 2280 2TB</a></strong><br></span></p>\n<p><span style=\"font-size: 12pt;\">&nbsp;- <strong>PSU</strong>: <strong><a href=\"/nguon-may-tinh-corsair-hx1200-1200w-80-plus-platinum\">CORSAIR HX1200 - 1200 Watt 80 Plus Platinum</a></strong><br></span></p>\n<p style=\"text-align: center;\">&nbsp;<img style=\"display: block; margin-left: auto; margin-right: auto;\" src=\"/media/lib/25-01-2022/1601_263088988_448030870221384_8094589584882783698_n.jpg\" alt=\"\" width=\"75%\"> <span style=\"font-size: 8pt; color: #000000; font-family: 'times new roman', times;\">*Góc nhìn từ trên xuống của em nó.</span></p>\n<p>&nbsp;</p>\n<p><span style=\"font-size: 12pt;\">Và sau cùng là bộ combo tản nhiệt nước custom được thiết kế và thi công bởi anh Modder hàng đầu Nguyễn PC. uốn mình theo những điểm nhấn của Z Tower là những đường ống dẫn nhiệt chất liệu kim loại cùng màu với chiếc case đến từ thương hiệu EKWB. EKWB cũng là hãng thi công phần Block CPU cho main ASUS ROG Z590 Maximus XIII Extreme Glacial. Tất nhiên block tản nhiệt nước cho 2 VGA 3090 24GB cũng sẽ đến từ thương hiệu EKWB để đồng bộ và tối ưu hiệu năng cho chiếc PC khủng long này. Phần quạt tản nhiệt mang lại sắc màu và làm mát cho case là Fan Case Lian-Li UNI Fan SL120 Triple Black</span></p>\n<p>&nbsp;<img style=\"display: block; margin-left: auto; margin-right: auto;\" src=\"/media/lib/25-01-2022/1601_263760215_448030916888046_6718609397543459540_n.jpg\" alt=\"\" width=\"75%\"></p>\n<p><span style=\"font-size: 12pt;\">1 Phần cũng khá quan trọng là chi phí cuối cùng của em nó lên đến <strong>400.000.000 VNĐ</strong></span></p>\n<p><span style=\"font-size: 12pt;\">với mức chi phí cực khủng và độ hiếm của case thì <strong><a href=\"/case-inwin-z-tower\">Inwin Z Tower Limited Edition No069</a></strong> Xứng đáng TOP 1 anh em nhé.</span></p>\n                    </div>\n                    <div class=\"box-content-des-vm\">\n                        <a href=\"javascript:void(0)\" onclick=\"showProDetailDes()\">Xem thêm</a>\n                    </div>\n                </div>"},{"name":"NPC Tequoia - Bộ case Phanteks Enthoo Evolv X","tech":"\n                    <div class=\"content\">\n<p><span style=\"font-size: 10pt;\">&nbsp;</span></p>\n<table style=\"height: 197px;\" width=\"672\">\n<tbody>\n<tr>\n<td><span style=\"font-size: 10pt;\"><strong>CPU&nbsp;</strong></span></td>\n<td><span style=\"font-size: 10pt;\">Intel Core i9-11900K</span></td>\n</tr>\n<tr>\n<td><span style=\"font-size: 10pt;\"><strong>MAINBOARD</strong></span></td>\n<td><span style=\"font-size: 10pt;\">ASUS Z590 ROG Maximus XIII Extreme GLACIAL</span></td>\n</tr>\n<tr>\n<td><span style=\"font-size: 10pt;\"><strong>RAM</strong></span></td>\n<td><span style=\"font-size: 10pt;\">Corsair DOMINATOR Platinum RGB 32GB (4 x 8GB) DDR4 Bus 3200MHz C16 - White</span></td>\n</tr>\n<tr>\n<td><span style=\"font-size: 10pt;\"><strong>PSU</strong></span></td>\n<td><span style=\"font-size: 10pt;\">ASUS ROG Thor 850W Platinum&nbsp;</span></td>\n</tr>\n<tr>\n<td><span style=\"font-size: 10pt;\"><strong>VGA</strong></span></td>\n<td><span style=\"font-size: 10pt;\">RTX TITAN</span></td>\n</tr>\n<tr>\n<td><span style=\"font-size: 10pt;\"><strong>CASE</strong></span></td>\n<td><span style=\"font-size: 10pt;\">Phanteks Enthoo Evolv X ATX&nbsp;</span></td>\n</tr>\n<tr>\n<td><span style=\"font-size: 10pt;\"><strong>Tản Nhiệt Nước</strong></span></td>\n<td>\n<p><span style=\"font-size: 10pt;\">Bitspower Pump D5 Vario and Full Bitspower water cooling components</span></p>\n<p><span style=\"font-size: 10pt;\">Coolant Mayhems X1 Clear Blue 1 Ltr Premixed V2</span></p>\n<p><span style=\"font-size: 10pt;\">Custom Distro Plate</span></p>\n</td>\n</tr>\n</tbody>\n</table>\n<p><span style=\"font-size: 10pt;\">&nbsp;</span></p>\n</div>\n                ","avatar":"public/images/images-e9a122e8-ff9a-44b7-849e-47c7f83b4874.jpg","price":"Liên","oldPrice":"","content":"<div class=\"title-n\">Đánh giá NPC Tequoia - Bộ case Phanteks Enthoo Evolv X</div>\n                <div class=\"list-n disaffter\">\n                    <div class=\"nd content-read\">\n                        <div class=\"content-text overflow-hidden position-relative\"><p><span style=\"font-size:15px;\">&nbsp;Cấu hình PC mà bạn không thể bỏ qua.</span></p>  <p><span style=\"font-size:15px;\">Lưu ý: Giá trọn bộ có thể thay đổi theo giá linh kiện mà không báo trước.&nbsp;</span></p></div>\n                    </div>\n                    <div class=\"box-content-des-vm\">\n                        <a href=\"javascript:void(0)\" onclick=\"showProDetailDes()\">Xem thêm</a>\n                    </div>\n                </div>"},{"name":"NPC Pyramid - Bộ case Inwin 925 Black Gold Edition","tech":"\n                    <p><span style=\"font-size: 10pt;\">&nbsp;</span></p>\n<table style=\"height: 338px;\" width=\"414\">\n<tbody>\n<tr>\n<td><span style=\"font-size: 10pt;\"><strong>CPU</strong></span></td>\n<td><span style=\"font-size: 10pt;\">Intel Core i9-10900K</span></td>\n</tr>\n<tr>\n<td><span style=\"font-size: 10pt;\"><strong>VGA</strong></span></td>\n<td><span style=\"font-size: 10pt;\">Gigabyte AORUS GeForce® RTX 3080 XTREME</span></td>\n</tr>\n<tr>\n<td><span style=\"font-size: 10pt;\"><strong>Main</strong></span></td>\n<td><span style=\"font-size: 10pt;\">Gigabyte Z490 AORUS XTREME</span></td>\n</tr>\n<tr>\n<td><span style=\"font-size: 10pt;\"><strong>PSU</strong></span></td>\n<td><span style=\"font-size: 10pt;\">GIGABYTE AORUS P850W 80 PLUS GOLD</span></td>\n</tr>\n<tr>\n<td><span style=\"font-size: 10pt;\"><strong>Case</strong></span></td>\n<td><span style=\"font-size: 10pt;\">InWin 925 Full Tower</span></td>\n</tr>\n<tr>\n<td><span style=\"font-size: 10pt;\"><strong>Ram</strong></span></td>\n<td><span style=\"font-size: 10pt;\">Corsair DOMINATOR Platinum RGB 32GB (4 x 8GB) DDR4 Bus 3000MHz C15</span></td>\n</tr>\n<tr>\n<td><span style=\"font-size: 10pt;\"><strong>SSD</strong></span></td>\n<td><span style=\"font-size: 10pt;\">Gigabyte AORUS Gen4 7000s SSD 1TB</span></td>\n</tr>\n<tr>\n<td><span style=\"font-size: 10pt;\"><strong>Fan</strong></span></td>\n<td><span style=\"font-size: 10pt;\">3x Fan Corsair QL120 RGB</span></td>\n</tr>\n<tr>\n<td><span style=\"font-size: 10pt;\"><strong>Cooling</strong></span></td>\n<td><span style=\"font-size: 10pt;\">Bitspower Pump D5 Vario and Full Bitspower water cooling components</span></td>\n</tr>\n<tr>\n<td><span style=\"font-size: 10pt;\"><strong>Nước tản nhiệt</strong></span></td>\n<td><span style=\"font-size: 10pt;\">Coolant Mayhems X1 Clear 1 Ltr Premixed V2</span></td>\n</tr>\n<tr>\n<td><span style=\"font-size: 10pt;\">&nbsp;</span></td>\n<td><span style=\"font-size: 10pt;\">3x Custom Distro Plate.</span></td>\n</tr>\n</tbody>\n</table>\n                ","avatar":"public/images/images-0e187e37-7e3f-4a46-b895-b1994d688100.jpg","price":"Liên","oldPrice":"","content":"<div class=\"title-n\">Đánh giá NPC Pyramid - Bộ case Inwin 925 Black Gold Edition</div>\n                <div class=\"list-n disaffter\">\n                    <div class=\"nd content-read\">\n                        <div class=\"content-text overflow-hidden position-relative\"><p><span style=\"font-size:15px;\">Trọn bộ tản nhiệt nước Bitspower cao cấp được custom bởi Nguyễn PC cho case Inwin 925 được mod lại màu vàng gold theo yêu cầu khách hàng với bộ cấu hình máy tính đáp ứng nhu cầu sử dụng của khách hàng.&nbsp;</span></p></div>\n                    </div>\n                    <div class=\"box-content-des-vm\">\n                        <a href=\"javascript:void(0)\" onclick=\"showProDetailDes()\">Xem thêm</a>\n                    </div>\n                </div>"},{"name":"NPC Knight - Bộ case Cougar Blazer (Mid Tower)","tech":"\n                    <div class=\"title\"><span style=\"font-size: 10pt;\">&nbsp;</span></div>\n<div class=\"content\">\n<table style=\"height: 425px;\" width=\"540\">\n<tbody>\n<tr>\n<td><span style=\"font-size: 10pt;\"><strong>CPU</strong></span></td>\n<td><span style=\"font-size: 10pt;\">Intel Core i9-11900K</span></td>\n</tr>\n<tr>\n<td><span style=\"font-size: 10pt;\"><strong>Main</strong></span></td>\n<td><span style=\"font-size: 10pt;\">MSI Z590 GAMING FORCE</span></td>\n</tr>\n<tr>\n<td><span style=\"font-size: 10pt;\"><strong>Ram</strong></span></td>\n<td><span style=\"font-size: 10pt;\">G.Skill Trident Z Neo 16GB (2x8GB) DDR4 3200MHz</span></td>\n</tr>\n<tr>\n<td><span style=\"font-size: 10pt;\"><strong>VGA</strong></span></td>\n<td><span style=\"font-size: 10pt;\">MSI RTX 3080 Ti SUPRIM 12G</span></td>\n</tr>\n<tr>\n<td><span style=\"font-size: 10pt;\"><strong>SSD</strong></span></td>\n<td>\n<p><span style=\"font-size: 10pt;\">ADATA XPG SX6000 512GB</span></p>\n<p><span style=\"font-size: 10pt;\">SAMSUNG 970 EVO PLUS 2TB</span></p>\n</td>\n</tr>\n<tr>\n<td><span style=\"font-size: 10pt;\"><strong>PSU</strong></span></td>\n<td><span style=\"font-size: 10pt;\">MSI MPG A850GF - 850W</span></td>\n</tr>\n<tr>\n<td><span style=\"font-size: 10pt;\"><strong>Case</strong></span></td>\n<td><span style=\"font-size: 10pt;\">Cougar Blazer (Mid Tower)</span></td>\n</tr>\n<tr>\n<td><span style=\"font-size: 10pt;\">&nbsp;</span></td>\n<td><span style=\"font-size: 10pt;\">Cooler Master Sleeved Extension Cable Kit (Red)</span></td>\n</tr>\n<tr>\n<td><span style=\"font-size: 10pt;\"><strong>Fan</strong></span></td>\n<td><span style=\"font-size: 10pt;\">4 x Fan Bitspower Njord</span></td>\n</tr>\n<tr>\n<td><span style=\"font-size: 10pt;\">&nbsp;</span></td>\n<td><span style=\"font-size: 10pt;\">Custom Distro Plate</span></td>\n</tr>\n</tbody>\n</table>\n</div>\n                ","avatar":"public/images/images-11d782f1-c6b2-4500-b158-c955ffa5bb5f.jpg","price":"Liên","oldPrice":"","content":"<div class=\"title-n\">Đánh giá NPC Knight - Bộ case Cougar Blazer (Mid Tower)</div>\n                <div class=\"list-n disaffter\">\n                    <div class=\"nd content-read\">\n                        <div class=\"content-text overflow-hidden position-relative\"><p><span style=\"font-size:15px;\">Phiên bản kết hợp vỏ case Cougar Blazer cùng linh kiện tản nhiệt nước Bitspower tạo nên sản phẩm vô cùng độc đáo như một chiến binh thép.</span></p></div>\n                    </div>\n                    <div class=\"box-content-des-vm\">\n                        <a href=\"javascript:void(0)\" onclick=\"showProDetailDes()\">Xem thêm</a>\n                    </div>\n                </div>"},{"name":"NPC Shadow - Bộ case Lian-Li O11D Mini Mid-Tower (Black)","tech":"\n                    <div class=\"title\"><span style=\"font-size: 10pt;\">&nbsp;</span></div>\n<div class=\"content\">\n<table style=\"height: 451px;\" width=\"545\">\n<tbody>\n<tr>\n<td><span style=\"font-size: 10pt;\"><strong>CPU</strong></span></td>\n<td><span style=\"font-size: 10pt;\">Intel Core i7 11700K</span></td>\n</tr>\n<tr>\n<td><span style=\"font-size: 10pt;\"><strong>Main</strong></span></td>\n<td><span style=\"font-size: 10pt;\">ASUS ROG STRIX Z590-I GAMING WIFI</span></td>\n</tr>\n<tr>\n<td><span style=\"font-size: 10pt;\"><strong>Ram</strong></span></td>\n<td><span style=\"font-size: 10pt;\">Corsair DOMINATOR Platinum RGB 16GB (2 x 8GB) DDR4 Bus 3200MHz C16</span></td>\n</tr>\n<tr>\n<td><span style=\"font-size: 10pt;\"><strong>PSU</strong></span></td>\n<td><span style=\"font-size: 10pt;\">Cooler Master MWE GOLD 850 - V2</span></td>\n</tr>\n<tr>\n<td><span style=\"font-size: 10pt;\"><strong>SSD</strong></span></td>\n<td><span style=\"font-size: 10pt;\">KLEVV CRAS C700 RGB 240GB</span></td>\n</tr>\n<tr>\n<td><span style=\"font-size: 10pt;\"><strong>VGA</strong></span></td>\n<td><span style=\"font-size: 10pt;\">ASUS TUF Gaming GeForce RTX 3070 OC</span></td>\n</tr>\n<tr>\n<td><span style=\"font-size: 10pt;\"><strong>Case</strong></span></td>\n<td><span style=\"font-size: 10pt;\">Lian-Li O11D Mini-X Mid-Tower Black</span></td>\n</tr>\n<tr>\n<td><span style=\"font-size: 10pt;\">&nbsp;</span></td>\n<td><span style=\"font-size: 10pt;\">LIAN LI Strimer RGB 24 PIN</span></td>\n</tr>\n<tr>\n<td><span style=\"font-size: 10pt;\"><strong>Fan</strong></span></td>\n<td><span style=\"font-size: 10pt;\">2 x Fan Lian Li SL120 Black (3PCS)</span></td>\n</tr>\n<tr>\n<td><span style=\"font-size: 10pt;\"><strong>Nước tản nhiệt</strong></span></td>\n<td><span style=\"font-size: 10pt;\">Coolant Mayhems X1 1 Ltr Premixed V2</span></td>\n</tr>\n<tr>\n<td><span style=\"font-size: 10pt;\">&nbsp;</span></td>\n<td><span style=\"font-size: 10pt;\">Bitspower Pump D5 Vario and Full Bitspower water cooling components</span></td>\n</tr>\n<tr>\n<td><span style=\"font-size: 10pt;\">&nbsp;</span></td>\n<td><span style=\"font-size: 10pt;\">Custom Distro Plate</span></td>\n</tr>\n</tbody>\n</table>\n</div>\n                ","avatar":"public/images/images-d578b0fe-ad6a-432f-a048-34b6a08e3139.jpg","price":"Liên","oldPrice":"","content":"<div class=\"title-n\">Đánh giá NPC Shadow - Bộ case Lian-Li O11D Mini Mid-Tower (Black)</div>\n                <div class=\"list-n disaffter\">\n                    <div class=\"nd content-read\">\n                        <div class=\"content-text overflow-hidden position-relative\"><p><span style=\"font-size:15px;\">Mẫu case Lian-Li Mini cho năm 2021, điểm nhấn bởi tấm nước được gia công trực tiếp tại Nguyễn PC tạo không gian cho thiết kế hệ thống tản nhiệt nước Bitspower một cách tốt nhất.&nbsp;</span></p>  <p><span style=\"font-size:15px;\">Lưu ý: Giá trọn bộ có thể thay đổi theo giá linh kiện mà không báo trước.&nbsp;</span></p></div>\n                    </div>\n                    <div class=\"box-content-des-vm\">\n                        <a href=\"javascript:void(0)\" onclick=\"showProDetailDes()\">Xem thêm</a>\n                    </div>\n                </div>"},{"name":"NPC Dragon Blood - Bộ case Thermaltake Core P5","tech":"\n                    <p><span style=\"font-size: 10pt;\">&nbsp;</span></p>\n<table style=\"height: 200px;\" width=\"619\">\n<tbody>\n<tr>\n<td><span style=\"font-size: 10pt;\"><strong>Main</strong></span></td>\n<td><span style=\"font-size: 10pt;\">ASUS CROSSHAIR VIII FORMULA X570 (AMD Socket AM4)</span></td>\n</tr>\n<tr>\n<td><span style=\"font-size: 10pt;\"><strong>CPU</strong></span></td>\n<td><span style=\"font-size: 10pt;\">AMD Ryzen 9 5900X</span></td>\n</tr>\n<tr>\n<td><span style=\"font-size: 10pt;\"><strong>Ram</strong></span></td>\n<td><span style=\"font-size: 10pt;\">Corsair DOMINATOR PLATINUM RGB 32GB (4x8GB)</span></td>\n</tr>\n<tr>\n<td><span style=\"font-size: 10pt;\"><strong>PSU</strong></span></td>\n<td><span style=\"font-size: 10pt;\">FSP Power Supply HYDRO PTM</span></td>\n</tr>\n<tr>\n<td><span style=\"font-size: 10pt;\"><strong>VGA</strong></span></td>\n<td><span style=\"font-size: 10pt;\">VGA ASUS ROG Strix GeForce RTX 3080 OC</span></td>\n</tr>\n<tr>\n<td><span style=\"font-size: 10pt;\"><strong>Case</strong></span></td>\n<td><span style=\"font-size: 10pt;\">Thermaltake Core P5</span></td>\n</tr>\n<tr>\n<td><span style=\"font-size: 10pt;\"><strong>SSD</strong></span></td>\n<td><span style=\"font-size: 10pt;\">Samsung 970 EVO Plus PCIe NVMe&nbsp;</span><span style=\"font-size: 10pt;\">500GB</span></td>\n</tr>\n<tr>\n<td><span style=\"font-size: 10pt;\"><strong>Pump</strong></span></td>\n<td><span style=\"font-size: 10pt;\">Bitspower Pump D5 Vario and Full Bitspower water cooling components.</span></td>\n</tr>\n<tr>\n<td><span style=\"font-size: 10pt;\"><strong>Fan</strong></span></td>\n<td><span style=\"font-size: 10pt;\">4x Touchaqua Notos Xtal 120 DGRB</span></td>\n</tr>\n<tr>\n<td><span style=\"font-size: 10pt;\"><strong>Nước Tản Nhiệt</strong></span></td>\n<td><span style=\"font-size: 10pt;\">Mayhems X1 Red 1 Ltr Premixed V2.</span></td>\n</tr>\n<tr>\n<td><span style=\"font-size: 10pt;\"><strong>Tấm Nước</strong></span></td>\n<td><span style=\"font-size: 10pt;\">2x NGUYENPC Custom Distro Plate.</span></td>\n</tr>\n</tbody>\n</table>\n<p><span style=\"font-size: 10pt;\">&nbsp;</span></p>\n                ","avatar":"public/images/images-a1755771-f460-4f2a-8efe-85b0276b5d27.jpg","price":"Liên","oldPrice":"","content":"<div class=\"title-n\">Đánh giá NPC Dragon Blood - Bộ case Thermaltake Core P5</div>\n                <div class=\"list-n disaffter\">\n                    <div class=\"nd content-read\">\n                        <div class=\"content-text overflow-hidden position-relative\"><p>Với mainboard ASUS ROG X570 CROSSHAIR VIII FORMULA AM4 trang bị những tính năng thời thượng được xem là một sản phẩm hướng tới game thủ và người dùng chuyên nghiệp kết hợp cùng AMD Ryzen 9 5900X là bộ xử lý nhanh nhất từng được thử nghiệm cho đến thời điểm hiện tại.</p>  <p>Điểm nhấn của case còn ở nguồn FSP Power Supply HYDRO PTM sử dụng giải pháp làm mát bằng chất lỏng tiên tiến được phát triển bởi Bitspower nên có hầu hết mọi thứ để làm hài lòng người dùng khó tính.</p>  <p>Hệ thống tản nhiệt sử dụng nước làm mát màu đỏ không chỉ hài hoà về màu sắc mà còn tạo sức hút cho các đường dẫn với các ống đứng thẳng tắp như chịu lực đỡ cho tấm nước giúp case trở nên mạnh mẽ hơn.</p>  <p>&nbsp;</p></div>\n                    </div>\n                    <div class=\"box-content-des-vm\">\n                        <a href=\"javascript:void(0)\" onclick=\"showProDetailDes()\">Xem thêm</a>\n                    </div>\n                </div>"},{"name":"NPC Snow White - Bộ case Thermaltake View 51","tech":"\n                    <div class=\"title\"><span style=\"font-size: 10pt;\">&nbsp;</span></div>\n<div class=\"content\">\n<table style=\"height: 307px;\" width=\"551\">\n<tbody>\n<tr>\n<td><span style=\"font-size: 10pt;\"><strong>CPU</strong></span></td>\n<td><span style=\"font-size: 10pt;\">Intel Core i7-10700K&nbsp;</span></td>\n</tr>\n<tr>\n<td><span style=\"font-size: 10pt;\"><strong>Main</strong></span></td>\n<td><span style=\"font-size: 10pt;\">Mainboard Colorful CVN Z490 Gaming Frozen</span></td>\n</tr>\n<tr>\n<td><span style=\"font-size: 10pt;\"><strong>VGA</strong></span></td>\n<td><span style=\"font-size: 10pt;\">ColorFul iGame GeForce RTX 3090 Advanced&nbsp;</span></td>\n</tr>\n<tr>\n<td><span style=\"font-size: 10pt;\"><strong>Ram</strong></span></td>\n<td><span style=\"font-size: 10pt;\">TeamGroup T-FORCE Xtreem ARGB 16GB (2 x 8GB) DDR4 3200MHz</span></td>\n</tr>\n<tr>\n<td><span style=\"font-size: 10pt;\"><strong>SSD</strong></span></td>\n<td><span style=\"font-size: 10pt;\">T-FORCE DELTA MAX 500GB 2.5\" LED&nbsp;</span></td>\n</tr>\n<tr>\n<td><span style=\"font-size: 10pt;\"><strong>PSU</strong></span></td>\n<td><span style=\"font-size: 10pt;\">Asus ROG Strix 750W Gold&nbsp;</span></td>\n</tr>\n<tr>\n<td><span style=\"font-size: 10pt;\"><strong>Case</strong></span></td>\n<td><span style=\"font-size: 10pt;\">Thermaltake View 51 TG ARGB White</span></td>\n</tr>\n<tr>\n<td><span style=\"font-size: 10pt;\"><strong>Fan</strong></span></td>\n<td>\n<p><span style=\"font-size: 10pt;\">Fan Thermaltake Riing Quad 12 RGB Radiator&nbsp;</span></p>\n<p><span style=\"font-size: 10pt;\">Fan TT Premium Edition 3 Fan Pack x2&nbsp;</span></p>\n</td>\n</tr>\n<tr>\n<td><span style=\"font-size: 10pt;\"><strong>Cooling</strong></span></td>\n<td><span style=\"font-size: 10pt;\">Bitspower Pump D5 Vario and Full Bitspower water cooling components</span></td>\n</tr>\n<tr>\n<td><span style=\"font-size: 10pt;\"><strong>Nước tản nhiệt</strong></span></td>\n<td><span style=\"font-size: 10pt;\">Coolant Mayhems X1 Clear 1 Ltr Premixed V2</span></td>\n</tr>\n<tr>\n<td><span style=\"font-size: 10pt;\">&nbsp;</span></td>\n<td><span style=\"font-size: 10pt;\">1x Custom Distro Plate</span></td>\n</tr>\n</tbody>\n</table>\n</div>\n                ","avatar":"public/images/images-72fbe575-bfd6-4a76-a9c7-493e7a838a51.jpg","price":"Liên","oldPrice":"","content":"<div class=\"title-n\">Đánh giá NPC Snow White - Bộ case Thermaltake View 51</div>\n                <div class=\"list-n disaffter\">\n                    <div class=\"nd content-read\">\n                        <div class=\"content-text overflow-hidden position-relative\"><p><span style=\"font-size:15px;\">Vừa qua, Nguyễn PC có cơ hội để thực hiện 1 hệ thống PC mạnh mẽ với vỏ case Thermaltake View 51, và để làm nên sự thành công của dự án lần này phải kể đến đơn vị tài trợ Network Hub Vietnam, là nhà phân phối linh kiện máy tính hàng đầu tại Việt Nam.</span></p>  <p><span style=\"font-size:15px;\">Thermaltake View 51 là một phiên bản nâng cấp tinh tế về ngoại hình và sự bố trí linh kiện linh hoạt của dòng sản phẩm View Series. Case có thiết kế thoáng với 2 quạt 200mm mang lại lượng Airflow dồi dào cùng các linh kiện cao cấp sẽ là sản phẩm hoàn hảo dành cho các game thủ.</span></p>  <p><span style=\"font-size:15px;\">Kết hợp cùng bộ tản nhiệt nước custom Bitspower – một thương hiệu nổi tiếng cho việc xây dựng hệ thống tản nhiệt nước cùng nước tản nhiệt Mayhems giúp các linh kiện tản nhiệt hoạt động bền bỉ theo thời gian.</span></p>  <p><span style=\"font-size:15px;\">Tấm nước được thiết kế riêng cho thẩm mĩ cao và tối ưu việc lắp đặt tản nhiệt nước trong Case, với mục tiêu giúp người dùng tiếp cận đến sản phẩm và lắp tản nhiệt nước tại nhà một cách dễ dàng nhất. Khách hàng sẽ có một góc nhìn hoàn toàn khác về vỏ case Thermaltake View 51 - tuy mang sự hầm hố cho game thủ nhưng vẫn uyển chuyển bởi các đường nước và hệ thống LED ARGB.</span></p>  <p><span style=\"font-size:15px;\">Khách hàng có nhu cầu lắp đặt máy vui lòng nhắn tin cho chúng tôi qua facebook: m.me/nguyenpc.vn</span></p>  <p><span style=\"font-size:15px;\">Hoặc liên hệ trực tiếp hotline 0909226607 để được tư vấn chi tiết.&nbsp;</span></p>  <p>&nbsp;</p></div>\n                    </div>\n                    <div class=\"box-content-des-vm\">\n                        <a href=\"javascript:void(0)\" onclick=\"showProDetailDes()\">Xem thêm</a>\n                    </div>\n                </div>"},{"name":"NPC Dursley - Bộ case Inwin 925 Full-Tower cùng bộ tản nhiệt nước Bitspower","tech":"\n                    <div class=\"title\">&nbsp;</div>\n<div class=\"content\">\n<table style=\"height: 473px;\" width=\"554\">\n<tbody>\n<tr>\n<td><span style=\"font-size: 10pt;\"><strong>CPU</strong></span></td>\n<td><span style=\"font-size: 10pt;\">Intel Core i9 9900K</span></td>\n</tr>\n<tr>\n<td><span style=\"font-size: 10pt;\"><strong>Main</strong></span></td>\n<td><span style=\"font-size: 10pt;\">MSI MEG Z390 ACE LGA1151v2</span></td>\n</tr>\n<tr>\n<td><span style=\"font-size: 10pt;\"><strong>Ram</strong></span></td>\n<td><span style=\"font-size: 10pt;\">G.SKILL Trident Z Royal Gold RGB 32GB (2 x 16GB) 3000MHz DDR4</span></td>\n</tr>\n<tr>\n<td><span style=\"font-size: 10pt;\"><strong>SSD</strong></span></td>\n<td><span style=\"font-size: 10pt;\">SSD Adata XPG SPECTRIX S40G RGB 256GB PCIe NVMe 3x4</span></td>\n</tr>\n<tr>\n<td><span style=\"font-size: 10pt;\"><strong>HDD</strong></span></td>\n<td><span style=\"font-size: 10pt;\">Ổ cứng Western Digital Caviar Green 3TB 64MB cache</span></td>\n</tr>\n<tr>\n<td><span style=\"font-size: 10pt;\"><strong>VGA</strong></span></td>\n<td><span style=\"font-size: 10pt;\">VGA MSI RTX 2080 Gaming X Trio 8G</span></td>\n</tr>\n<tr>\n<td><span style=\"font-size: 10pt;\"><strong>Case</strong></span></td>\n<td><span style=\"font-size: 10pt;\">INWIN 925 Full-Towe</span></td>\n</tr>\n<tr>\n<td><span style=\"font-size: 10pt;\"><strong>PSU</strong></span></td>\n<td><span style=\"font-size: 10pt;\">PSU AORUS AP850GM 850W 80 Plus Gold Modular</span></td>\n</tr>\n<tr>\n<td><span style=\"font-size: 10pt;\"><strong>Cooling&nbsp;</strong></span></td>\n<td><span style=\"font-size: 10pt;\">Bộ tản nhiệt nước bitspower</span></td>\n</tr>\n<tr>\n<td>&nbsp;</td>\n<td><span style=\"font-size: 10pt;\">Lian-li Strimer Plus 24 pin and 8x2 pin</span></td>\n</tr>\n</tbody>\n</table>\n</div>\n                ","avatar":"public/images/images-bad6641a-8fd3-4ea0-b69f-c1cccdd44621.jpg","price":"Liên","oldPrice":"","content":"<div class=\"title-n\">Đánh giá NPC Dursley - Bộ case Inwin 925 Full-Tower cùng bộ tản nhiệt nước Bitspower</div>\n                <div class=\"list-n disaffter\">\n                    <div class=\"nd content-read\">\n                        <div class=\"content-text overflow-hidden position-relative\"><p>Trọn bộ PC gaming kèm hệ thống tản nhiệt nước Bitspower custom được chọn lọc bởi những linh kiện từ các thương hiệu hàng đầu.<br>Bộ tản nhiệt nước Bitspower được lắp đặt với linh kiện chính hãng, được phân phối trực tiếp tại Nguyễn PC.&nbsp;</p></div>\n                    </div>\n                    <div class=\"box-content-des-vm\">\n                        <a href=\"javascript:void(0)\" onclick=\"showProDetailDes()\">Xem thêm</a>\n                    </div>\n                </div>"},{"name":"NPC Cedric - Bộ case Phanteks Enthoo Evolv X cùng bộ tản nhiệt nước Bitspower","tech":"\n                    <div class=\"title\">&nbsp;</div>\n<div class=\"content\">\n<table style=\"height: 394px;\" width=\"508\">\n<tbody>\n<tr>\n<td><span style=\"font-size: 10pt;\"><strong>CPU</strong></span></td>\n<td><span style=\"font-size: 10pt;\">AMD Ryzen 9 5950X</span></td>\n</tr>\n<tr>\n<td><span style=\"font-size: 10pt;\"><strong>Main</strong></span></td>\n<td><span style=\"font-size: 10pt;\">Gigabyte X570 AORUS MASTER</span></td>\n</tr>\n<tr>\n<td><span style=\"font-size: 10pt;\"><strong>Ram&nbsp;</strong></span></td>\n<td><span style=\"font-size: 10pt;\">GIGABYTE AORUS RGB 16GB (2x8GB) DDR4 3200MHz</span></td>\n</tr>\n<tr>\n<td><span style=\"font-size: 10pt;\"><strong>PSU</strong></span></td>\n<td><span style=\"font-size: 10pt;\">Super Flower Leadex Platinum SE 1000W - 80 Plus Platinum, Fully Modular</span></td>\n</tr>\n<tr>\n<td><span style=\"font-size: 10pt;\"><strong>SSD</strong></span></td>\n<td><span style=\"font-size: 10pt;\">Crucial P1 1TB NVMe 3D-NAND M.2 PCIe Gen3 x4 CT1000P1SSD8</span></td>\n</tr>\n<tr>\n<td><span style=\"font-size: 10pt;\"><strong>VGA</strong></span></td>\n<td><span style=\"font-size: 10pt;\">GIGABYTE AORUS GeForce RTX 2080 SUPER</span></td>\n</tr>\n<tr>\n<td><span style=\"font-size: 10pt;\"><strong>Case</strong></span></td>\n<td><span style=\"font-size: 10pt;\">Phanteks Enthoo Evolv ITX Black</span></td>\n</tr>\n<tr>\n<td><span style=\"font-size: 10pt;\"><strong>Fan</strong></span></td>\n<td>\n<p><span style=\"font-size: 10pt;\">3x Noctua NF-A12x25</span></p>\n<p><span style=\"font-size: 10pt;\">1x Corsair LL140 RGB 140mm</span></p>\n</td>\n</tr>\n<tr>\n<td><span style=\"font-size: 10pt;\"><strong>Cooling</strong></span></td>\n<td><span style=\"font-size: 10pt;\">Bộ tản nhiệt nước Bitspower</span></td>\n</tr>\n<tr>\n<td><span style=\"font-size: 10pt;\"><strong>Nước tản nhiệt</strong></span></td>\n<td><span style=\"font-size: 10pt;\">Mayhems X1 Blue 1 Ltr Premixed V2</span></td>\n</tr>\n</tbody>\n</table>\n</div>\n<p><span style=\"font-size: 10pt;\">&nbsp;</span></p>\n                ","avatar":"public/images/images-a4af35e5-5d11-4411-a7ca-6a4faf3bf39e.jpg","price":"Liên","oldPrice":"","content":"<div class=\"title-n\">Đánh giá NPC Cedric - Bộ case Phanteks Enthoo Evolv X cùng bộ tản nhiệt nước Bitspower</div>\n                <div class=\"list-n disaffter\">\n                    <div class=\"nd content-read\">\n                        <div class=\"content-text overflow-hidden position-relative\"><p>&nbsp;Trọn bộ PC gaming kèm hệ thống tản nhiệt nước Bitspower custom được chọn lọc bởi những linh kiện từ các thương hiệu hàng đầu.</p>  <p>Bộ tản nhiệt nước Bitspower được lắp đặt với linh kiện chính hãng, được phân phối trực tiếp tại Nguyễn PC.&nbsp;</p></div>\n                    </div>\n                    <div class=\"box-content-des-vm\">\n                        <a href=\"javascript:void(0)\" onclick=\"showProDetailDes()\">Xem thêm</a>\n                    </div>\n                </div>"},{"name":"Sumire - NZXT H710i Matte White","tech":"\n                    <table style=\"height: 410px;\" width=\"457\">\n<tbody>\n<tr>\n<td><span style=\"font-size: 10pt;\"><strong>CPU</strong></span></td>\n<td><span style=\"font-size: 10pt;\">Intel Core i9-12900KF</span></td>\n</tr>\n<tr>\n<td><span style=\"font-size: 10pt;\"><strong>MAIN</strong></span></td>\n<td><span style=\"font-size: 10pt;\">Z690-A Gaming Wifi D4</span></td>\n</tr>\n<tr>\n<td><span style=\"font-size: 10pt;\"><strong>RAM</strong></span></td>\n<td><span style=\"font-size: 10pt;\">G.Skill Trident Z RGB Royal Elite Silver 16GB (2x8GB) DDR4 3600MHz</span></td>\n</tr>\n<tr>\n<td><span style=\"font-size: 10pt;\"><strong>SSD</strong></span></td>\n<td><span style=\"font-size: 10pt;\">MSI SPATIUM M390 1TB M.2 Gen 3</span></td>\n</tr>\n<tr>\n<td><span style=\"font-size: 10pt;\"><strong>VGA&nbsp;</strong></span></td>\n<td><span style=\"font-size: 10pt;\">RTX 3070 Vision OC 8G</span></td>\n</tr>\n<tr>\n<td><strong><span style=\"font-size: 10pt;\">PSU&nbsp;</span></strong></td>\n<td><span style=\"font-size: 10pt;\">850W 80 Plus GOLD MODULAR</span></td>\n</tr>\n</tbody>\n</table>\n                ","avatar":"public/images/images-ea453097-a3d7-423e-a899-f34d8d39a257.jpg","price":"Liên","oldPrice":"","content":"<div class=\"title-n\">Đánh giá Sumire - NZXT H710i Matte White</div>\n                <div class=\"list-n disaffter\">\n                    <div class=\"nd content-read\">\n                        <div class=\"content-text overflow-hidden position-relative\">\n<p style=\"text-align: justify;\">Trọn bộ PC NZXT H710i được kết hợp hài hoà trong màu trắng tinh khôi mang đến vẻ ngoài thanh lịch nhưng không kém phần sang trọng.<br>&nbsp;<br>Vỏ case H710i được thiết kế với màu trắng tinh tế, có các cải tiến về thiết kế bao gồm khay SSD được thiết kế lại, giá đỡ bằng kính cường lực phẳng và nhiều điều chỉnh tốt để có trải nghiệm xây dựng thông minh hơn, ngoài nhiệm vụ điều khiển các hiệu ứng đèn LED của các linh kiện trong hệ sinh thái NZXT, thiết bị này còn được trang bị thêm một con chip siêu nhỏ giúp điều khiển đến 3 quạt lắp thêm, đồng thời hiển thị những thông số cơ bản như vòng quay/phút và hiệu điện thế. Hệ thống hỗ trợ đi dây thông minh, khay lắp radiator, quạt, ổ cứng có thể tháo lắp dễ dàng.</p>\n<p style=\"text-align: justify;\">Kết hợp hoàn hảo cùng vỏ case H710i chính là card đồ hoạ RTX 3070 VISION OC 8G được thiết kế đặc biệt dành cho người làm việc sáng tạo, có kiểu dáng thanh lịch, nhã nhặn, cung cấp cho các creater một sự lựa chọn tinh tế. Được trang bị hệ thống làm mát WINDFORCE 3X có các quạt cánh độc đáo 3 X 80mm, quay luân phiên, 5 ống dẫn nhiệt bằng đồng composite, GPU cảm ứng trực tiếp, quạt hoạt động 3D và cùng nhau tất cả các công nghệ cao cấp đó cung cấp khả năng tản nhiệt hiệu quả cao hơn.<br>&nbsp;<br>Không thể không nói đến, đó chính là bo mạch chủ Z490 VISION G được sử dụng cùng tone trắng làm chủ đạo với sự kết hợp những chi tiết nhôm bạc tạo nên sự sang trọng và cao cấp.<br>Sản phẩm hỗ trợ người dùng 4 khe cắm RAM có khả năng có khả năng ép xung XMP lên đến 5000MHz, hỗ trợ tới 6 cổng kết nối SATA 3, cùng 2 khe M.2 giúp bạn có thể thoải mái lưu trữ, mở rộng dữ liệu.<br>&nbsp;<br>Shop kết hợp sản phẩm cùng SSD Samsung 970 EVO Plus với bộ đệm dung lượng đến 78 GB để cải thiện tốc độ ghi được tốt hơn.<br>&nbsp;<br>Dù bạn là một gamer hay designer, marketer thì đây vẫn là sản phẩm phù hợp cho bạn.</p>\n<p style=\"text-align: justify;\">Nếu bạn lo lắng về chính sách bảo hành, Nguyễn PC đảm bảo các linh kiện máy tính vẫn được bảo hành chính hãng theo chính hãng. Đồng thời, Nguyễn PC bảo hành 12 tháng cho bộ tản nhiệt nhiệt nước Bitspower custom.</p>\n<p style=\"text-align: justify;\">Nếu bạn muốn dùng ngân sách cho nhiều kế hoạch khác nhau và muốn lựa chọn mua trả góp, Nguyễn PC hoàn toàn đáp ứng được điều đó cho bạn (Tham khảo trả góp TẠI ĐÂY)</p>\n<p style=\"text-align: justify;\">Hãy liên hệ cho chúng tôi khi bạn cần sản phẩm:</p>\n<p style=\"text-align: justify;\">Địa chỉ: 86/19/2 Thích Quảng Đức, Phường 5, quận Phú Nhuận, Tp.Hồ Chí Minh<br>Facebook: https://www.facebook.com/nguyenpc.vn &nbsp;<br>Hotline: 0909226607<br>Youtube channel: https://bitly.com.vn/ylxi28&nbsp;<br>Giờ làm việc: 9h00 – 21h00</p>\n</div>\n                    </div>\n                    <div class=\"box-content-des-vm\">\n                        <a href=\"javascript:void(0)\" onclick=\"showProDetailDes()\">Xem thêm</a>\n                    </div>\n                </div>"}]